palmera_ethtx/__init__.py
palmera_ethtx/exceptions.py
palmera_ethtx/palmera_ethtx.py
palmera_ethtx/decoders/__init__.py
palmera_ethtx/decoders/decoder_service.py
palmera_ethtx/decoders/abi/__init__.py
palmera_ethtx/decoders/abi/abc.py
palmera_ethtx/decoders/abi/balances.py
palmera_ethtx/decoders/abi/calls.py
palmera_ethtx/decoders/abi/decoder.py
palmera_ethtx/decoders/abi/events.py
palmera_ethtx/decoders/abi/transfers.py
palmera_ethtx/decoders/abi/helpers/__init__.py
palmera_ethtx/decoders/abi/helpers/utils.py
palmera_ethtx/decoders/decoders/__init__.py
palmera_ethtx/decoders/decoders/errors.py
palmera_ethtx/decoders/decoders/parameters.py
palmera_ethtx/decoders/decoders/semantics.py
palmera_ethtx/decoders/semantic/__init__.py
palmera_ethtx/decoders/semantic/abc.py
palmera_ethtx/decoders/semantic/balances.py
palmera_ethtx/decoders/semantic/calls.py
palmera_ethtx/decoders/semantic/decoder.py
palmera_ethtx/decoders/semantic/events.py
palmera_ethtx/decoders/semantic/metadata.py
palmera_ethtx/decoders/semantic/transfers.py
palmera_ethtx/decoders/semantic/helpers/__init__.py
palmera_ethtx/decoders/semantic/helpers/utils.py
palmera_ethtx/models/__init__.py
palmera_ethtx/models/_types.py
palmera_ethtx/models/base_model.py
palmera_ethtx/models/decoded_model.py
palmera_ethtx/models/objects_model.py
palmera_ethtx/models/semantics_model.py
palmera_ethtx/models/w3_model.py
palmera_ethtx/providers/__init__.py
palmera_ethtx/providers/ens_provider.py
palmera_ethtx/providers/signature_provider.py
palmera_ethtx/providers/web3_provider.py
palmera_ethtx/providers/etherscan/__init__.py
palmera_ethtx/providers/etherscan/client.py
palmera_ethtx/providers/etherscan/contracts.py
palmera_ethtx/providers/etherscan/etherscan_provider.py
palmera_ethtx/providers/node/__init__.py
palmera_ethtx/providers/node/connection_base.py
palmera_ethtx/providers/node/pool.py
palmera_ethtx/providers/semantic_providers/__init__.py
palmera_ethtx/providers/semantic_providers/base.py
palmera_ethtx-1.0.8.dist-info/LICENSE
palmera_ethtx-1.0.8.dist-info/METADATA
palmera_ethtx-1.0.8.dist-info/WHEEL
palmera_ethtx-1.0.8.dist-info/top_level.txt
palmera_ethtx-1.0.8.dist-info/RECORD
