Metadata-Version: 2.1
Name: palmera-ethtx
Version: 1.0.8
Summary: Fork EthTx transaction decoder by Palmera
Home-page: https://github.com/keyper-labs/palmera-ethtx
Author: Palmera
Author-email: general@palmeradao.xyz
License: Apache-2.0 License
Classifier: Operating System :: POSIX :: Linux
Classifier: Programming Language :: Python :: 3.8
Classifier: Programming Language :: Python :: 3.9
Requires-Python: >=3.7.0
License-File: LICENSE
Requires-Dist: toml
Requires-Dist: pymongo <4.0,>=3.10.0
Requires-Dist: dnspython >=2.0.0
Requires-Dist: mongoengine <0.27.0
Requires-Dist: mongomock
Requires-Dist: web3 <7.0.0,>=6.0.0
Requires-Dist: python-dotenv
Requires-Dist: requests
Requires-Dist: pydantic ==1.10.12
Requires-Dist: setuptools
Requires-Dist: wheel
Requires-Dist: twine
